timestamper.py
timestamper-0.0.1.dist-info/LICENSE
timestamper-0.0.1.dist-info/METADATA
timestamper-0.0.1.dist-info/WHEEL
timestamper-0.0.1.dist-info/top_level.txt
timestamper-0.0.1.dist-info/RECORD
