Metadata-Version: 2.1
Name: timestamper
Version: 0.0.1
Summary: samll helper for recording time usage
Home-page: https://github.com/beat-no/timestamper
Author: Øystein S. Haaland
Author-email: oystein@beat.no
License: UNKNOWN
Platform: UNKNOWN
